{
  "id": "wakened_huorns",
  "name": "Wakened Huorns",
  "region": "the Old Forest, the deep glades",
  "tier": "Fell",
  "recLevel": 18,
  "resupply": "none",
  "rewards": "heart-wood; a path through the dark eaves",
  "flavorIntro": "The trees have waked in anger. Bark turns hard as iron, roots heave and seize, and a heavy green drowsiness hangs in the close air.",
  "stages": [
    {
      "stageId": "main",
      "label": "Wakened Huorns",
      "type": "attrition",
      "objective": "kill",
      "durationSec": 2400,
      "resolve": 5000,
      "drain": 52,
      "spike": 80,
      "spikeIntervalSec": 9,
      "physMitPct": 42,
      "dread": 0,
      "shadow": 0,
      "disease": 0,
      "cold": 0,
      "heat": 0,
      "wakefulness": 4,
      "stageFlavor": ""
    }
  ]
}